<?xml version="1.0" encoding="UTF-8"?>
<!DOCTYPE mapper PUBLIC "-//mybatis.org//DTD Mapper 3.0//EN" "http://mybatis.org/dtd/mybatis-3-mapper.dtd">

<mapper namespace="io.renren.modules.order.dao.RemarkDao">

	<!-- 可根据自己的需求，是否要使用 -->
    <resultMap type="io.renren.modules.order.entity.RemarkEntity" id="remarkMap">
        <result property="remarkId" column="remark_id"/>
        <result property="orderId" column="order_id"/>
        <result property="remark" column="remark"/>
        <result property="userId" column="user_id"/>
        <result property="updateTime" column="update_time"/>
        <result property="type" column="type"/>
        <result property="remarkType" column="remark_type"/>
    </resultMap>


</mapper>